{
  "contributors": 13,
  "createdAt": "2026-02-03T15:08:25Z",
  "fetchedAt": "2026-07-21T06:14:45.061Z",
  "forks": 314,
  "latestRelease": {
    "publishedAt": "2026-07-20T05:50:18Z",
    "tag": "v0.7.5"
  },
  "license": "MIT",
  "openIssues": 224,
  "pushedAt": "2026-07-20T16:19:53Z",
  "repo": "zhukunpenglinyutong/desktop-cc-gui",
  "sizeKB": 83578,
  "stars": 3645,
  "weeklyCommits": [
    0,
    0,
    0,
    0,
    0,
    0,
    0,
    0,
    0,
    0,
    0,
    0,
    0,
    0,
    0,
    0,
    0,
    0,
    0,
    0,
    0,
    0,
    0,
    0,
    0,
    0,
    0,
    42,
    55,
    35,
    39,
    63,
    46,
    83,
    85,
    59,
    56,
    113,
    335,
    248,
    254,
    195,
    175,
    184,
    193,
    227,
    149,
    185,
    79,
    108,
    190,
    39
  ]
}
